mdl_style.py
markdown_link_style/__init__.py
markdown_link_style/_version.py
markdown_link_style/logging.py
markdown_link_style-0.2.1.dist-info/COPYING
markdown_link_style-0.2.1.dist-info/METADATA
markdown_link_style-0.2.1.dist-info/WHEEL
markdown_link_style-0.2.1.dist-info/entry_points.txt
markdown_link_style-0.2.1.dist-info/top_level.txt
markdown_link_style-0.2.1.dist-info/RECORD
