Metadata-Version: 2.1
Name: markdown-link-style
Version: 0.2.1
Summary: Switch between inline and footnote link style in markdown documents.
Home-page: https://git.ricketyspace.net/markdown-link-style
Author: rsiddharth
Author-email: s@ricketyspace.net
License: GNU General Public License version 3 or later
Keywords: markdown link inline footnote style
Platform: GNU/Linux
Classifier: Development Status :: 2 - Pre-Alpha
Classifier: Environment :: Console
Classifier: Intended Audience :: Developers
Classifier: Intended Audience :: End Users/Desktop
Classifier: License :: OSI Approved :: GNU General Public License v3 or later (GPLv3+)
Classifier: Operating System :: POSIX :: Linux
Classifier: Programming Language :: Python :: 3.5
Classifier: Programming Language :: Python :: 3 :: Only
Classifier: Topic :: Documentation
Classifier: Topic :: Text Processing :: General
Classifier: Topic :: Utilities
Requires-Dist: mistune (<1,>0.8)
